access/__init__.py
access/access_rule.py
access/pet_utils.py
access/utils.py
vmaccess-0.1.1.dist-info/DESCRIPTION.rst
vmaccess-0.1.1.dist-info/METADATA
vmaccess-0.1.1.dist-info/RECORD
vmaccess-0.1.1.dist-info/WHEEL
vmaccess-0.1.1.dist-info/entry_points.txt
vmaccess-0.1.1.dist-info/metadata.json
vmaccess-0.1.1.dist-info/top_level.txt
vmaccess-0.1.1.dist-info/zip-safe
