Metadata-Version: 2.0
Name: vmaccess
Version: 0.1.1
Summary: Initial triage for VM Access Control
Home-page: https://github.corp.ebay.com/GPSCCOE/vmaccess
Author: danyachen
Author-email: danyachen@ebay.com
License: UNKNOWN
Keywords: python vm access control ssh sudo
Platform: UNKNOWN
Requires-Dist: requests
